twain_extensions/__init__.py
twain_extensions/enums.py
twain_extensions/frame.py
twain_extensions/generate/__init__.py
twain_extensions/generate/generate.py
twain_extensions/generate/template.py
twain_extensions/registries/__init__.py
twain_extensions/registries/audio_capabilities.py
twain_extensions/registries/capability.py
twain_extensions/registries/general_capabilities.py
twain_extensions/registries/image_capabilities.py
pytwain_extensions-0.1.0.dist-info/WHEEL
pytwain_extensions-0.1.0.dist-info/METADATA
pytwain_extensions-0.1.0.dist-info/RECORD
