Metadata-Version: 2.3
Name: pytwain-extensions
Version: 0.1.0
Summary: A Python library that extends pytwain with pythonic design to make working with the TWAIN api easier. Built on TWAIN 2.5 specification.
Author: Jonathan Costa
Author-email: Jonathan Costa <jonathanleonhard.costa@gmail.com>
Classifier: Topic :: Multimedia :: Graphics :: Capture :: Scanners
Requires-Python: >=3.10
